piicrgmms/__init__.py
piicrgmms/classes/__init__.py
piicrgmms/classes/_base.py
piicrgmms/classes/_bayesian_gaussian_mixture.py
piicrgmms/classes/_cluster_merger_gui.py
piicrgmms/classes/_data_frame.py
piicrgmms/classes/_gaussian_mixture_model.py
piicrgmms/classes/_phase_first_gaussian_model.py
piicrgmms/sklearn_mixture_piicr/__init__.py
piicrgmms/sklearn_mixture_piicr/_base.py
piicrgmms/sklearn_mixture_piicr/_bayesian_mixture.py
piicrgmms/sklearn_mixture_piicr/_gaussian_mixture.py
piicrgmms/sklearn_mixture_piicr/_phase_constrained_gaussian_mixture.py
piicrgmms/sklearn_mixture_piicr/_strict_bayesian_mixture.py
piicrgmms-0.1.4.dist-info/LICENSE.txt
piicrgmms-0.1.4.dist-info/LICENSE_scikit_learn.txt
piicrgmms-0.1.4.dist-info/METADATA
piicrgmms-0.1.4.dist-info/WHEEL
piicrgmms-0.1.4.dist-info/top_level.txt
piicrgmms-0.1.4.dist-info/RECORD
