Metadata-Version: 2.1
Name: piicrgmms
Version: 0.1.4
Summary: A data analysis package for PI-ICR Mass Spectrometry
Home-page: https://pypi.org/project/piicrgmms/
Author: Colin Weber
Author-email: colin.weber.27@gmail.com
License: UNKNOWN
Project-URL: Homepage, https://pypi.org/project/piicrgmms/
Project-URL: Source code, https://github.com/colinweber27/piicrgmms
Project-URL: Download, https://pypi.org/project/piicrgmms/#files
Keywords: Gaussian Mixture Models,Clustering Algorithms,Machine Learning,Mass Spectrometry
Platform: UNKNOWN
Classifier: Programming Language :: Python :: 3
Classifier: License :: OSI Approved :: MIT License
Classifier: Intended Audience :: Science/Research
Classifier: Natural Language :: English
Classifier: Operating System :: Microsoft :: Windows
Classifier: Topic :: Scientific/Engineering
Classifier: Topic :: Scientific/Engineering :: Artificial Intelligence
Classifier: Topic :: Scientific/Engineering :: Physics
Requires-Python: >=3.6
License-File: LICENSE.txt
License-File: LICENSE_scikit_learn.txt
Requires-Dist: scikit-learn
Requires-Dist: pandas
Requires-Dist: matplotlib
Requires-Dist: lmfit
Requires-Dist: joblib
Requires-Dist: tqdm
Requires-Dist: pillow
Requires-Dist: webcolors
